{
  "version": "v4",
  "repo": "borisyankov/DefinitelyTyped",
  "ref": "master",
  "path": "client/.tsd",
  "bundle": "client/.tsd/tsd.d.ts",
  "installed": {
    "angularjs/angular.d.ts": {
      "commit": "0fff32b558aa91ba24cfca5479aba02e4ef2fafe"
    },
    "jquery/jquery.d.ts": {
      "commit": "0fff32b558aa91ba24cfca5479aba02e4ef2fafe"
    },
    "angularjs/angular-route.d.ts": {
      "commit": "0fff32b558aa91ba24cfca5479aba02e4ef2fafe"
    },
    "lodash/lodash.d.ts": {
      "commit": "0fff32b558aa91ba24cfca5479aba02e4ef2fafe"
    }
  }
}
